aws_shelltools/__init__.py
aws_shelltools/awsassumerole.py
aws_shelltools/awsconfig.py
aws_shelltools/awstoken.py
aws_shelltools/shelltools_setup.py
aws_shelltools/util.py
aws_shelltools/shell_functions/shell_functions.bash
aws_shelltools-0.1.5.dist-info/LICENCE.txt
aws_shelltools-0.1.5.dist-info/METADATA
aws_shelltools-0.1.5.dist-info/WHEEL
aws_shelltools-0.1.5.dist-info/entry_points.txt
aws_shelltools-0.1.5.dist-info/top_level.txt
aws_shelltools-0.1.5.dist-info/RECORD
