Metadata-Version: 2.1
Name: aws-shelltools
Version: 0.1.5
Summary: Yet another set of scripts and shell functions for managing AWS profiles and cross account access.
Home-page: https://github.com/ashleygould/aws-shelltools
Author: Ashley Gould
Author-email: agould@ucop.edu
License: MIT
Keywords: aws awscli session
Platform: UNKNOWN
Classifier: Development Status :: 4 - Beta
Classifier: Intended Audience :: Developers
Classifier: Intended Audience :: System Administrators
Classifier: License :: OSI Approved :: MIT License
Classifier: Programming Language :: Python :: 3.6
Classifier: Programming Language :: Python :: 3.7
Requires-Dist: awscli
Requires-Dist: boto3
Requires-Dist: botocore
Requires-Dist: docopt
Requires-Dist: aws-orgs
